inkbird_ble/__init__.py
inkbird_ble/parser.py
inkbird_ble/py.typed
inkbird_ble-1.1.0.dist-info/LICENSE
inkbird_ble-1.1.0.dist-info/METADATA
inkbird_ble-1.1.0.dist-info/WHEEL
inkbird_ble-1.1.0.dist-info/RECORD
